{
  "task_id": "301382197452",
  "stage": "v3_english",
  "job_function": "Automotive",
  "language": "英语",
  "scenario": "Scenario: A professional business discussion conducted in English. Keep the conversation practical, decision-oriented, and easy to follow.\n[Topic context: 新能源车型上市前的区域投放和销售策略讨论]",
  "core_content": "Core requirements: include concrete facts, assigned actions, open risks, dependencies, and a clear next-step summary in English.\n[Keywords: 投放节奏, 渠道准备, 卖点表达, 库存规划, 区域反馈, 动作安排]",
  "people_count": 2,
  "word_count": 2000,
  "seed": 1617508420,
  "effective_params": {
    "scenario_head": "Scenario: A professional business discussion conducted in En",
    "core_head": "Core requirements: include concrete facts, assigned actions,",
    "people_count": 2,
    "word_count": 2000,
    "language": "英语"
  },
  "debug_info": {
    "rewrite_info": {
      "rewrite_triggered": true,
      "rewrite_count": 2,
      "fill_turns": 0,
      "seed": 3938249380,
      "is_from_v2": false,
      "placeholder_violations": 34,
      "duplicate_intro_fixed": 1,
      "naturalness_applied": true,
      "naturalness_language": "English",
      "naturalness_rewrites": 5
    },
    "line_count": 32,
    "total_chars": 2285,
    "seed": 1617508420,
    "generator": "embedded_bundle_v1"
  },
  "stats": {
    "line_count": 32,
    "total_chars": 2285,
    "speaker_distribution": {
      "Speaker 1": 19,
      "Speaker 2": 13
    }
  },
  "quality": {
    "passed": true,
    "score": 80.0,
    "max_score": 100.0,
    "metrics": {
      "line_count": 32,
      "total_chars": 2285,
      "marker_count": 0,
      "chinese_ratio": 0.0,
      "kana_ratio": 0.0,
      "korean_ratio": 0.0,
      "speaker_distribution": {
        "Speaker 1": 19,
        "Speaker 2": 13
      },
      "target_word_count": 2000,
      "unique_line_ratio": 1.0
    },
    "findings": [
      {
        "code": "missing_core_marker",
        "severity": "warning",
        "message": "缺少核心标记",
        "details": {}
      }
    ]
  }
}